Workbook

Sheet 00 Summary
A1: Bachat Gat SaaS - User Test Cases
A2: Use this workbook to test registration, setup, approvals, calculations, dashboard numbers, security and reports.
A4: Area | B4: What to test | C4: Expected result
A5: Login/Register | B5: Duplicate email, OTP resend, forgot password, Google login fallback | C5: Valid users register/login; duplicate email is blocked; reset and OTP links work after Supabase redirect setup.
A6: Group & Members | B6: Create group, creator becomes admin member, add members with unique username | C6: Only current group members appear; group code is visible; hidden groups can be managed.
A7: Setup | B7: Group/member/finance/period/role/approval setup | C7: Null member setup falls back to group setup; setup approval status shows pending approver.
A8: Legacy Migration | B8: Group opening and member opening migration | C8: Approval flow applies when approvers exist; only one history row is shown per member migration.
A9: Transactions | B9: Savings, excess, loan repayment allocation, group expense split | C9: Completed entries only affect dashboard; excess is savings; expenses create member expense share lines.
A10: Loans | B10: Member loan request, admin approval, interest and repayment split | C10: Loan request goes to approvers/admin; disbursement and repayments update outstanding values.
A11: Corrections | B11: Adjustment and reversal approvals | C11: Approved records are not edited directly; corrections create child entries and audit history.
A12: Dashboards | B12: Current month and overall summaries | C12: Dashboard matches expected output sheet after sample test data is entered.
A13: Security | B13: Member/admin/product owner access and group isolation | C13: No data from other groups appears in current group session.
A17: Recommended sample period: May 2026. Sample group: Maitri Test Group (BG-T01). Members: Asha Admin, Bhavna Member, Chitra Approver.

Sheet 01 Login Register
A1: Login And Registration Tests
A2: Run these before financial testing so the user and group identities are clean.
A4: TC ID | B4: Scenario | C4: Input / Steps | D4: Expected Result | E4: Actual Result | F4: Status
A5: LR-01 | B5: Register new user | C5: Full name: Asha Admin; email: asha.test@example.com; mobile optional; set password | D5: User is created. Profile name shows Asha Admin. No random member name is created.
A6: LR-02 | B6: Duplicate email blocked | C6: Try registering again with asha.test@example.com | D6: Registration is stopped with readable message: account already exists.
A7: LR-03 | B7: Resend OTP | C7: Use expired/invalid OTP link, click Resend OTP | D7: New verification email is sent and message disappears automatically after a few seconds.
A8: LR-04 | B8: Forgot password | C8: Click forgot password and open email link | D8: Redirect opens app reset password page. Password can be updated.
A9: LR-05 | B9: Create group | C9: Login as Asha, create Maitri Test Group | D9: Asha is inserted in members table for this group and assigned Admin role.
A10: LR-06 | B10: Group list details | C10: Open Your Groups | D10: Group name, group code, and creator name are visible.
A11: LR-07 | B11: Hide/unhide group | C11: Hide one group, then open hidden groups and unhide | D11: Hidden group is removed from normal list and returns after unhide.
A12: LR-08 | B12: Member registers later | C12: Add Bhavna with email bhavna.test@example.com, then register using same email | D12: Bhavna can see all groups where that email is a member and can create a new group if needed.

Sheet 02 Setup Tests
A1: Setup Tests
A2: Use null member setup values to confirm fallback to group setup.
A4: TC ID | B4: Setup Area | C4: Input Values | D4: Expected Result | E4: Actual Result | F4: Status
A5: ST-01 | B5: Group setup | C5: Monthly saving 1000; interest 2%; penalty 100; loan limit 10000; tenure 6; due day 10 | D5: Values save or go for approval based on approver setup. Notification shows only changed fields.
A6: ST-02 | B6: Member setup null fallback | C6: Asha custom saving blank; loan limit blank; tenure blank; interest blank | D6: Stored as NULL, not 0. Transactions/loans use group setup values.
A7: ST-03 | B7: Member setup override | C7: Bhavna custom saving 1500; loan limit 7000; tenure blank | D7: Bhavna uses saving 1500 and loan limit 7000; tenure still falls back to group 6.
A8: ST-04 | B8: Approval setup | C8: Make Chitra approver. Admin remains checked for creator. | D8: Admin checkbox is checked for creator; Chitra receives approval requests.
A9: ST-05 | B9: Pending setup approval panel | C9: Make any setup change while approver exists | D9: Bottom of setup page shows setup type, changed values, status, and pending approver.
A10: ST-06 | B10: Period default closed | C10: Create May 2026 period but do not open | D10: Transactions are allowed only if no other period is open. Period itself remains Closed until opened.
A11: ST-07 | B11: Open selected period | C11: Select May 2026, click Open selected period | D11: May 2026 opens, all other periods close. Not April 2026.
A12: ST-08 | B12: Required field marker | C12: Open setup forms | D12: Only calculation/login mandatory fields show * mark.

Sheet 03 Legacy Migration
A1: Legacy Migration Tests
A2: Migration values should create approved/pending financial entries and clean history.
A4: TC ID | B4: Scenario | C4: Input Values | D4: Expected Result | E4: Actual Result | F4: Status
A5: LM-01 | B5: Group opening migration | C5: Opening bank 5000; old group gain 600; old expense 300; date 2026-05-01 | D5: If approver exists, status Pending and visible in approvals. After approval it affects dashboard.
A6: LM-02 | B6: Member opening Asha | C6: Saving 2000; joined date 2026-05-01 | D6: One member history row only. No duplicate source rows. No unused share earned/bank balance columns shown.
A7: LM-03 | B7: Member opening Chitra | C7: Saving 1000; optional old loan 3000; old interest 120; old penalty 50 | D7: Migration creates transaction/loan opening entries as per architecture after approval.
A8: LM-04 | B8: Excess in migration | C8: Saving setup 1000, migration received amount 1300 | D8: Split shows 1000 saving + 300 excess. Both are included in savings.
A9: LM-05 | B9: No approvers configured | C9: Remove approver setup, save member migration | D9: Migration auto completes and immediately reflects in dashboard.

Sheet 04 Transactions
A1: Transaction And Expense Tests
A2: Completed transactions only should affect dashboard.
A4: TC ID | B4: Scenario | C4: Input Values | D4: Expected Split / Result | E4: Actual Result | F4: Status
A5: TR-01 | B5: Asha saving | C5: Member Asha; date 2026-05-05; amount 1000 | D5: Saving 1000. If no approver setup, status Completed.
A6: TR-02 | B6: Bhavna saving with excess | C6: Member Bhavna; date 2026-05-06; amount 2000 | D6: Saving 1500 + excess 500. Dashboard saving includes full 2000.
A7: TR-03 | B7: Loan repayment preview | C7: Asha loan outstanding 5000; payment date 2026-05-20; amount 1200 | D7: Before save preview shows saving 1000, interest about 33, principal about 167.
A8: TR-04 | B8: Edit allocation validation | C8: Try interest above calculated value | D8: Blocked. Interest cannot exceed calculated interest.
A9: TR-05 | B9: Principal validation | C9: Try principal above outstanding amount | D9: Blocked. Principal cannot exceed outstanding principal.
A10: TR-06 | B10: Penalty changed manually | C10: Increase penalty in edit allocation | D10: Excess adjusts first, then principal, then interest; remaining unpaid interest stays for next payment.
A11: TR-07 | B11: Group expense split | C11: Expense 300; lines Rent 200 and Bank charge 100 | D11: Header and lines total must match. Creates expense header/lines and member expense share 100 each for 3 active members.
A12: TR-08 | B12: Pending transaction | C12: Configure approver then save transaction | D12: Transaction remains Pending. It is not included in dashboard until all approvals complete.

Sheet 05 Loans Approvals
A1: Loan And Approval Tests
A2: Loan requests should go to approvers/admin and only become active after approval.
A4: TC ID | B4: Scenario | C4: Input Values | D4: Expected Result | E4: Actual Result | F4: Status
A5: LA-01 | B5: Member loan request | C5: Login as Asha/Bhavna member; loan amount 5000; reason optional/blank | D5: Member can request loan only for self. Request goes to approvers/admin.
A6: LA-02 | B6: Loan eligibility - account balance | C6: Account balance 5000; loan limit 10000; request 8000 | D6: Blocked. Eligible amount is only 5000.
A7: LA-03 | B7: Loan eligibility - setup limit | C7: Account balance 20000; member/group loan limit 10000; request 15000 | D7: Blocked because setup loan limit is less than requested amount.
A8: LA-04 | B8: Loan approval completion | C8: All approvers approve loan request | D8: Loan becomes Active and disbursement entry is created.
A9: LA-05 | B9: Approval action confirm | C9: Click Approve/Reject action | D9: Confirmation popup appears. After confirm, buttons are disabled for that approval.
A10: LA-06 | B10: Pending from label | C10: Create loan with multiple approvers | D10: Loan/approval row shows whose approval is pending.
A11: LA-07 | B11: Oldest loan repayment priority | C11: Member has two active loans; create repayment | D11: Interest is collected for all loans first, then principal against oldest loan first.

Sheet 06 Corrections
A1: Adjustment And Reversal Tests
A2: Approved financial records must not be directly edited or deleted.
A4: TC ID | B4: Scenario | C4: Input Values | D4: Expected Result | E4: Actual Result | F4: Status
A5: CR-01 | B5: Partial adjustment | C5: Original collection 2000; correct amount 1500 | D5: Create adjustment -500 as child entry. If approvers exist, pending until all approve.
A6: CR-02 | B6: Full reversal | C6: Wrong member selected for 1000 collection | D6: Create full negative reversal child entry. Original record stays unchanged.
A7: CR-03 | B7: Adjustment approval | C7: Approver approves adjustment | D7: Only after approval adjustment affects dashboard and audit history.
A8: CR-04 | B8: Reversal audit | C8: Open audit history for reversed transaction | D8: Audit shows parent transaction, reversal action, changed by, date and remarks.
A9: CR-05 | B9: No direct edit/delete | C9: Try editing approved transaction directly | D9: UI only offers View, Adjust, Reverse, Audit History.

Sheet 07 Role Security
A1: Role, Privacy And Product Owner Tests
A2: Current group session must never show another group data.
A4: TC ID | B4: Scenario | C4: Steps | D4: Expected Result | E4: Actual Result | F4: Status
A5: RS-01 | B5: Member view only | C5: Login as member without admin role | D5: Setup, transactions and admin loan actions are hidden/restricted. Dashboards/reports/contact visible.
A6: RS-02 | B6: Approver access | C6: Login as Chitra approver | D6: Approvals visible only for groups where Chitra is approver.
A7: RS-03 | B7: Group isolation dashboard | C7: Switch from BG-T01 to another group | D7: All dashboard, member, loan, contact, profile context changes to selected group only.
A8: RS-04 | B8: Profile context | C8: Open profile while current group is BG-T01 | D8: Shows logged-in user profile, not another member from another group.
A9: RS-05 | B9: Product owner login | C9: Login with katgroupsupport@gmail.com | D9: Product Owner page visible. Profile does not show normal member details from unrelated group.
A10: RS-06 | B10: Product owner disputes | C10: Open support disputes and attachment | D10: Attachment downloads; chat replies are visible only to that user and group session.
A11: RS-07 | B11: Popup readability | C11: Trigger validation error | D11: Popup background is readable and disappears automatically after a few seconds.

Sheet 09 Calculation Details
A1: Sample Calculation Inputs
A2: These values feed the expected dashboard sheet. Replace Actual values while testing if your data differs.
A4: Input | B4: Value | C4: Notes
A5: Active members | B5: 3 | C5: Asha, Bhavna, Chitra
A6: Group monthly saving | B6: 1000 | C6: Group setup
A7: Bhavna monthly saving override | B7: 1500 | C7: Member setup override
A8: Monthly interest rate | B8: 0.02 | C8: 2% per month
A9: Loan due day | B9: 10 | C9: Finance setup
A10: Opening bank balance | B10: 5000 | C10: Group legacy opening
A11: Opening group gain | B11: 600 | C11: Legacy group earning from old interest/penalty
A12: Opening group expense | B12: 300 | C12: Legacy group expense
A13: Asha migrated saving | B13: 2000 | C13: Member legacy opening
A14: Chitra migrated saving | B14: 1000 | C14: Member legacy opening
A15: Asha May saving | B15: 1000 | C15: TR-01
A16: Bhavna May saving plus excess | B16: 2000 | C16: TR-02: 1500 saving + 500 excess
... A27: Chitra distributed gain | B27: 11 | C27: 33 / 3 simple sample

Sheet 08 Dashboard Expected
A1: Dashboard Expected Output
A2: Expected values after entering the sample data and completing required approvals.
A4: Dashboard Field | B4: Expected Value | C4: Formula / Meaning | D4: Actual App Value | E4: Pass/Fail
A5: Total savings | B5: ='09 Calculation Details'!B13+'09 Calculation Details'!B14+'09 Calculation Details'!B15+'09 Calculation Details'!B16+'09 Calculation Details'!B18 -> 7200 | C5: Asha migrated + Chitra migrated + Asha saving + Bhavna saving/excess + repayment saving
A6: Collected in May 2026 | B6: ='09 Calculation Details'!B15+'09 Calculation Details'!B16+'09 Calculation Details'!B18+'09 Calculation Details'!B19+'09 Calculation Details'!B20 -> 5233 | C6: Savings + principal collected + interest collected + penalty. Excludes loan disbursed and expenses.
A7: Collected split - savings | B7: ='09 Calculation Details'!B15+'09 Calculation Details'!B16+'09 Calculation Details'!B18 -> 4200 | C7: Savings includes excess amount
A8: Collected split - principal | B8: ='09 Calculation Details'!B19 -> 1000 | C8: Principal collected this month
A9: Collected split - interest | B9: ='09 Calculation Details'!B20 -> 33 | C9: Interest collected this month
A10: Collected split - penalty | B10: ='09 Calculation Details'!B21 -> 167 | C10: Penalty collected this month
A11: Active loan count | B11: 1 | C11: Asha active loan
A12: Closed loan count till now | B12: 0 | C12: No closed loan in base sample
A13: Loans activated in May 2026 | B13: 1 | C13: Asha loan approved in May
A14: Loans disbursed till now count | B14: 1 | C14: One approved loan disbursement
A15: Active loan amount | B15: ='09 Calculation Details'!B17-'09 Calculation Details'!B19 -> 4000 | C15: Outstanding principal = disbursed - principal repaid
A16: Loan disbursed in May 2026 | B16: ='09 Calculation Details'!B17 -> 5000 | C16: Loan amount released in current month
A17: Loan disbursed till now | B17: ='09 Calculation Details'!B17 -> 5000 | C17: Total loan disbursement so far
A18: Loan repaid till now | B18: ='09 Calculation Details'!B19 -> 1000 | C18: Principal repaid so far
A19: Remaining account balance | B19: ='09 Calculation Details'!B9+B5+'09 Calculation Details'!B10-'09 Calculation Details'!B17-('09 Calculation Details'!B11+'09 Calculation Details'!B22) -> 6610 | C19: Opening bank + May collected + opening gain - loan disbursed - total expenses
A20: Remaining split - outstanding loan | B20: ='09 Calculation Details'!B17-'09 Calculation Details'!B19 -> 4000 | C20: Outstanding principal
A21: Remaining split - overall expense | B21: ='09 Calculation Details'!B11+'09 Calculation Details'!B22 -> 600 | C21: Opening expense + May expense
A22: Remaining split - gain | B22: ='09 Calculation Details'!B10+'09 Calculation Details'!B20+'09 Calculation Details'!B21 -> 5200 | C22: Opening gain + interest + penalty; not negative expense
A23: Remaining split - savings | B23: =B5 -> 7200 | C23: Same as total savings
A24: Member Asha savings | B24: ='09 Calculation Details'!B13+'09 Calculation Details'!B15+'09 Calculation Details'!B18 -> 4200 | C24: Savings field does not subtract expenses
A25: Member Asha gain | B25: ='09 Calculation Details'!B24 -> 100 | C25: Distributed gain from interest/penalty
A26: Member Asha expense | B26: ='09 Calculation Details'!B11/'09 Calculation Details'!B7+'09 Calculation Details'!B23 -> 300.4 | C26: Opening expense share + May expense share
A27: Member Asha outstanding loan | B27: ='09 Calculation Details'!B17-'09 Calculation Details'!B19 -> 4000 | C27: Active loan outstanding principal
A28: Member Asha share amount | B28: =B24+B25-B26-B27 -> -0.4 | C28: Savings + gain - expense - outstanding loan
A29: Member Asha next minimum due | B29: ='09 Calculation Details'!B5+'09 Calculation Details'!B20+'09 Calculation Details'!B21 -> 203 | C29: Saving setup + interest due + penalty due
A32: If your app uses weighted group-gain distribution instead of equal distribution, replace member gain rows with the weighted result while keeping the same dashboard principles.

Sheet 10 Final Regression
A1: Final End-To-End Regression
A2: Use this sheet after individual tests pass.
A4: Run Order | B4: End-to-End Flow | C4: Expected Result | D4: Actual Result | E4: Status
A5: 1 | B5: Register Asha, create group, verify creator admin/member | C5: Asha appears in member LOV and admin role setup.
A6: 2 | B6: Add Bhavna and Chitra, configure Chitra approver | C6: Only BG-T01 members are visible in BG-T01.
A7: 3 | B7: Open May 2026 period | C7: May opens, other periods close.
A8: 4 | B8: Enter group/member legacy migration and approve | C8: One clean history row per member; group opening has approval/history.
A9: 5 | B9: Enter savings/excess and group expense | C9: Dashboard savings include excess; expense is split to active members.
A10: 6 | B10: Request and approve loan | C10: Loan request appears in approvals and becomes active only after approvals complete.
A11: 7 | B11: Enter repayment | C11: Preview calculates interest before save and applies repayment to interest then principal.
A12: 8 | B12: Create adjustment/reversal and approve | C12: Dashboard updates only after approval; audit history is complete.
A13: 9 | B13: Login as member | C13: Member has view-only access and can request own loan.
A14: 10 | B14: Login as product owner | C14: Product owner dashboard, disputes, subscriptions and group inspection are visible without leaking wrong profile context.
A15: 11 | B15: Compare dashboard with expected output sheet | C15: All key dashboard values match or differences are explained by changed test values.
